aydin/__init__.py
aydin/_version.py
aydin/analysis/__init__.py
aydin/analysis/blind_spot_analysis.py
aydin/analysis/camera_simulation.py
aydin/analysis/correlation.py
aydin/analysis/dimension_analysis.py
aydin/analysis/empirical_noise_model.py
aydin/analysis/find_kernel.py
aydin/analysis/fsc.py
aydin/analysis/image_metrics.py
aydin/analysis/resolution_estimate.py
aydin/analysis/snr_estimate.py
aydin/analysis/demo/__init__.py
aydin/analysis/demo/demo_blind_spot_analysis.py
aydin/analysis/demo/demo_camera_simulation.py
aydin/analysis/demo/demo_correlation.py
aydin/analysis/demo/demo_correlation_simple.py
aydin/analysis/demo/demo_dimension_analysis.py
aydin/analysis/demo/demo_empirical_noise_model.py
aydin/analysis/demo/demo_fsc.py
aydin/analysis/demo/demo_resolution_estimate.py
aydin/analysis/demo/demo_snr_estimate.py
aydin/analysis/test/__init__.py
aydin/analysis/test/test_blind_spot_analysis.py
aydin/analysis/test/test_dimension_analysis.py
aydin/analysis/test/test_empirical_noise_model.py
aydin/analysis/test/test_fsc.py
aydin/analysis/test/test_image_metrics.py
aydin/analysis/test/test_resolution_estimate.py
aydin/analysis/test/test_snr_estimate.py
aydin/cli/__init__.py
aydin/cli/cli.py
aydin/cli/test/__init__.py
aydin/cli/test/test_cli.py
aydin/features/__init__.py
aydin/features/base.py
aydin/features/extensible_features.py
aydin/features/standard_features.py
aydin/features/demo/__init__.py
aydin/features/demo/demo_feature_generator.py
aydin/features/demo/demo_feature_generator_blind_spots.py
aydin/features/groups/__init__.py
aydin/features/groups/base.py
aydin/features/groups/correlation.py
aydin/features/groups/dct.py
aydin/features/groups/extract_kernels.py
aydin/features/groups/learned_conv.py
aydin/features/groups/lowpass.py
aydin/features/groups/median.py
aydin/features/groups/random.py
aydin/features/groups/spatial.py
aydin/features/groups/translations.py
aydin/features/groups/uniform.py
aydin/features/groups/demo/__init__.py
aydin-0.1.15.dist-info/LICENSE.txt
aydin-0.1.15.dist-info/METADATA
aydin-0.1.15.dist-info/WHEEL
aydin-0.1.15.dist-info/entry_points.txt
aydin-0.1.15.dist-info/top_level.txt
aydin-0.1.15.dist-info/RECORD
