Metadata-Version: 2.1
Name: aydin
Version: 0.1.15
Summary: Aydin - Denoising but chill
Home-page: https://royerlab.github.io/aydin/
Download-URL: https://github.com/royerlab/aydin
License: BSD 3-Clause
Classifier: Development Status :: 3 - Alpha
Classifier: Environment :: X11 Applications :: Qt
Classifier: Intended Audience :: Science/Research
Classifier: License :: OSI Approved :: BSD License
Classifier: Programming Language :: Python :: 3 :: Only
Classifier: Programming Language :: Python :: 3.9
Classifier: Programming Language :: Python :: 3.10
Classifier: Topic :: Scientific/Engineering
Classifier: Topic :: Scientific/Engineering :: Image Processing
Classifier: Operating System :: Microsoft :: Windows
Classifier: Operating System :: POSIX
Classifier: Operating System :: Unix
Classifier: Operating System :: MacOS
Requires-Python: >=3.9
License-File: LICENSE.txt
Requires-Dist: catboost (>=1.0.5)
Requires-Dist: Click (>=8.0.3)
Requires-Dist: czifile (>=2019.7.2)
Requires-Dist: Deprecated (>=1.2.13)
Requires-Dist: docstring-parser (>=0.13)
Requires-Dist: gdown (>=4.2.0)
Requires-Dist: importlib-metadata (>=4.10.0)
Requires-Dist: imageio (==2.21.1)
Requires-Dist: jsonpickle (==1.3.0)
Requires-Dist: lightgbm (>=3.3.1)
Requires-Dist: napari (==0.4.15)
Requires-Dist: nd2reader (>=3.3.0)
Requires-Dist: numba (>=0.55.1)
Requires-Dist: numpy (>=1.19.2)
Requires-Dist: protobuf (==3.20.1)
Requires-Dist: pynndescent (>=0.5.5)
Requires-Dist: PyQt5 (>=5.15.6)
Requires-Dist: QDarkStyle (==3.0.2)
Requires-Dist: qtpy (>=1.11.2)
Requires-Dist: scikit-image (==0.18.3)
Requires-Dist: scipy (>=1.7.3)
Requires-Dist: tensorflow (==2.8.1)
Requires-Dist: torch (>=1.10.1)
Requires-Dist: keras (==2.8.0)
Requires-Dist: zarr (>=2.12.0)
Requires-Dist: imagecodecs (==2022.2.22)
Requires-Dist: memoization (>=0.4.0)
Provides-Extra: bundle
Requires-Dist: catboost (==1.0.5) ; extra == 'bundle'
Requires-Dist: Click (==8.0.3) ; extra == 'bundle'
Requires-Dist: czifile (==2019.7.2) ; extra == 'bundle'
Requires-Dist: docstring-parser (==0.13) ; extra == 'bundle'
Requires-Dist: gdown (==4.2.0) ; extra == 'bundle'
Requires-Dist: importlib-metadata (==4.10.0) ; extra == 'bundle'
Requires-Dist: jsonpickle (==1.3.0) ; extra == 'bundle'
Requires-Dist: lightgbm (==3.3.1) ; extra == 'bundle'
Requires-Dist: napari (==0.4.12) ; extra == 'bundle'
Requires-Dist: nd2reader (==3.3.0) ; extra == 'bundle'
Requires-Dist: numba (==0.55.1) ; extra == 'bundle'
Requires-Dist: numpy (>=1.19.2) ; extra == 'bundle'
Requires-Dist: protobuf (==3.20.1) ; extra == 'bundle'
Requires-Dist: pynndescent (==0.5.5) ; extra == 'bundle'
Requires-Dist: PyQt5 (==5.15.6) ; extra == 'bundle'
Requires-Dist: QDarkStyle (==3.0.2) ; extra == 'bundle'
Requires-Dist: qtpy (==1.11.2) ; extra == 'bundle'
Requires-Dist: scikit-image (>=0.18.3) ; extra == 'bundle'
Requires-Dist: scipy (==1.7.3) ; extra == 'bundle'
Requires-Dist: tensorflow (==2.8.1) ; extra == 'bundle'
Requires-Dist: torch (==1.10.1) ; extra == 'bundle'
Requires-Dist: keras (==2.8.0) ; extra == 'bundle'
Requires-Dist: zarr (==2.4.0) ; extra == 'bundle'
Requires-Dist: imagecodecs (==2022.2.22) ; extra == 'bundle'
Requires-Dist: memoization (==0.4.0) ; extra == 'bundle'
